k3git/__init__.py
k3git/git_wrapper.py
k3git/gitopt.py
k3git/giturl.py
k3git-0.1.18.dist-info/licenses/LICENSE
k3git-0.1.18.dist-info/METADATA
k3git-0.1.18.dist-info/WHEEL
k3git-0.1.18.dist-info/top_level.txt
k3git-0.1.18.dist-info/RECORD
