Metadata-Version: 2.4
Name: k3git
Version: 0.1.18
Summary: wrapper of git command-line
Author-email: Zhang Yanpo <drdr.xp@gmail.com>
License: MIT
Project-URL: Homepage, https://github.com/pykit3/k3git
Project-URL: Documentation, https://k3git.readthedocs.io
Keywords: git,cli,commandline
Classifier: Development Status :: 4 - Beta
Classifier: Intended Audience :: Developers
Classifier: Topic :: Software Development :: Libraries
Classifier: License :: OSI Approved :: MIT License
Classifier: Programming Language :: Python :: 3
Classifier: Programming Language :: Python :: 3.9
Classifier: Programming Language :: Python :: 3.10
Classifier: Programming Language :: Python :: 3.11
Classifier: Programming Language :: Python :: 3.12
Requires-Python: >=3.9
License-File: LICENSE
Requires-Dist: k3str<0.2,>=0.1.1
Requires-Dist: k3ut<0.2,>=0.1.7
Requires-Dist: k3handy<0.2,>=0.1.12
Requires-Dist: k3fs<0.2,>=0.1.5
Provides-Extra: dev
Requires-Dist: pytest>=7.0; extra == "dev"
Requires-Dist: ruff; extra == "dev"
Requires-Dist: coverage; extra == "dev"
Provides-Extra: publish
Requires-Dist: build; extra == "publish"
Requires-Dist: twine; extra == "publish"
Requires-Dist: pk3; extra == "publish"
Provides-Extra: docs
Requires-Dist: mkdocs>=1.5; extra == "docs"
Requires-Dist: mkdocs-material>=9.0; extra == "docs"
Requires-Dist: mkdocstrings[python]>=0.24; extra == "docs"
Dynamic: license-file
